pySafetyNet_Attestation-0.0.5.dist-info/METADATA
pySafetyNet_Attestation-0.0.5.dist-info/RECORD
pySafetyNet_Attestation-0.0.5.dist-info/WHEEL
pySafetyNet_Attestation-0.0.5.dist-info/top_level.txt
safetynet_attestation/Attestation.py
safetynet_attestation/__init__.py
