Metadata-Version: 2.1
Name: pySafetyNet-Attestation
Version: 0.0.5
Summary: Verify JWS-attestations from Google's SafetyNet.
Home-page: https://github.com/RoosDaniel/SafetyNet-Attestation
Author: Daniel Roos
Author-email: daniel@roos.io
License: UNKNOWN
Platform: UNKNOWN
Classifier: Programming Language :: Python :: 3
Classifier: License :: OSI Approved :: MIT License
Classifier: Operating System :: OS Independent
Requires-Dist: pyOpenSSL
Requires-Dist: certvalidator
Requires-Dist: jwcrypto
Requires-Dist: requests
